airspot_dev/__init__.py
airspot_dev/containers/__init__.py
airspot_dev/containers/core.py
airspot_dev/containers/kubernetes.py
airspot_dev/pulumi_/__init__.py
airspot_dev/pulumi_/debug.py
airspot_dev/pulumi_/docker/__init__.py
airspot_dev/pulumi_/docker/builder.py
airspot_dev/pulumi_/gcp/__init__.py
airspot_dev/pulumi_/gcp/identity.py
airspot_dev/pulumi_/gcp/ingress.py
airspot_dev/pulumi_/gcp/networking.py
airspot_dev/pulumi_/gcp/vertex_ai.py
airspot_dev/pulumi_/gcp/web_application.py
airspot_dev/pulumi_/k8s/__init__.py
airspot_dev/pulumi_/k8s/application.py
airspot_dev/pulumi_/k8s/backend_config.py
airspot_dev/pulumi_/k8s/deployment.py
airspot_dev/pulumi_/k8s/namespace.py
airspot_dev/pulumi_/k8s/pvc.py
airspot_dev/pulumi_/k8s/secrets.py
airspot_dev/pulumi_/k8s/service.py
airspot_dev/pulumi_/k8s/stateful.py
airspot_dev_support-0.10.1.dist-info/METADATA
airspot_dev_support-0.10.1.dist-info/WHEEL
airspot_dev_support-0.10.1.dist-info/top_level.txt
airspot_dev_support-0.10.1.dist-info/RECORD
