Metadata-Version: 2.4
Name: airspot-dev-support
Version: 0.10.1
Summary: Airspot IaC support library
Requires-Python: >=3.12
Requires-Dist: dependency-injector>=4.46.0
Requires-Dist: pulumi>=3.160.0
Requires-Dist: pulumi-docker>=4.6.2
Requires-Dist: pulumi-kubernetes>=4.22.1
Requires-Dist: pulumi-gcp>=8.0.0
Requires-Dist: pydantic>=2.11.3
Requires-Dist: google-cloud-aiplatform>=1.111.0
